projen_modules/__init__.py
projen_modules/py.typed
projen_modules/_jsii/__init__.py
projen_modules/_jsii/projen-modules@1.1.68.jsii.tgz
projen_modules-1.1.68.dist-info/LICENSE
projen_modules-1.1.68.dist-info/METADATA
projen_modules-1.1.68.dist-info/WHEEL
projen_modules-1.1.68.dist-info/top_level.txt
projen_modules-1.1.68.dist-info/RECORD
